{"cameraMode":{"drawMode":0,"name":"Shaded","section":"Shading Mode"},"sceneLighting":false,"audioPlay":false,"sceneViewState":{"m_AlwaysRefresh":false,"showFog":true,"showSkybox":false,"showFlares":true,"showImageEffects":true,"showParticleSystems":true,"showVisualEffectGraphs":true,"m_FxEnabled":true},"in2DMode":false,"pivot":{"x":-0.17973029613494874,"y":1.5054326057434083,"z":-1.374064326286316},"rotation":{"x":-0.1413363367319107,"y":0.8369055390357971,"z":-0.2549411356449127,"w":-0.46314987540245058},"size":2.3078033924102785,"orthographic":false}